workflowlite/__init__.py
workflowlite/workflow.py
workflowlite-0.2.3.dist-info/LICENSE
workflowlite-0.2.3.dist-info/METADATA
workflowlite-0.2.3.dist-info/WHEEL
workflowlite-0.2.3.dist-info/top_level.txt
workflowlite-0.2.3.dist-info/RECORD
