Metadata-Version: 2.1
Name: workflowlite
Version: 0.2.3
Summary: a simple workflow engine
Home-page: https://github.com/c4pt0r/workflowlite
Author: Ed Huang
Author-email: dongxuhuang@yahoo.com
Classifier: Programming Language :: Python :: 3
Classifier: Operating System :: OS Independent
Requires-Python: >=3.6
License-File: LICENSE
